secret_transfer/__init__.py
secret_transfer/__main__.py
secret_transfer/app/__init__.py
secret_transfer/app/application.py
secret_transfer/app/settings.py
secret_transfer/cli.py
secret_transfer/context.py
secret_transfer/core/__init__.py
secret_transfer/core/base/__init__.py
secret_transfer/core/base/base.py
secret_transfer/core/base/proxy.py
secret_transfer/core/base/registry.py
secret_transfer/core/collection/__init__.py
secret_transfer/core/collection/base.py
secret_transfer/core/collection/proxy.py
secret_transfer/core/destination/__init__.py
secret_transfer/core/destination/base.py
secret_transfer/core/destination/proxy.py
secret_transfer/core/source/__init__.py
secret_transfer/core/source/base.py
secret_transfer/core/source/proxy.py
secret_transfer/core/transfer/__init__.py
secret_transfer/core/transfer/base.py
secret_transfer/core/transfer/proxy.py
secret_transfer/core/types.py
secret_transfer/default/__init__.py
secret_transfer/default/collection/__init__.py
secret_transfer/default/collection/default.py
secret_transfer/default/destination/__init__.py
secret_transfer/default/destination/bash_export.py
secret_transfer/default/destination/env.py
secret_transfer/default/destination/gh_cli_secrets.py
secret_transfer/default/source/__init__.py
secret_transfer/default/source/dot_env.py
secret_transfer/default/source/env.py
secret_transfer/default/source/preset.py
secret_transfer/default/source/user_input.py
secret_transfer/default/source/vault_cli_kv.py
secret_transfer/default/source/yc_cli_lockbox.py
secret_transfer/default/transfer/__init__.py
secret_transfer/default/transfer/default.py
secret_transfer/protocol/__init__.py
secret_transfer/protocol/base.py
secret_transfer/protocol/collection.py
secret_transfer/protocol/destination.py
secret_transfer/protocol/source.py
secret_transfer/protocol/transfer.py
secret_transfer/py.typed
secret_transfer/utils/__init__.py
secret_transfer/utils/cli/__init__.py
secret_transfer/utils/cli/base.py
secret_transfer-0.4.0.dist-info/METADATA
secret_transfer-0.4.0.dist-info/WHEEL
secret_transfer-0.4.0.dist-info/entry_points.txt
secret_transfer-0.4.0.dist-info/RECORD
