Metadata-Version: 2.1
Name: secret-transfer
Version: 0.4.0
Summary: Yaml-based secret manager for secret load/set/clean.
Home-page: https://github.com/ovsds/secret-transfer
License: MIT
Keywords: secret,transfer,yaml
Author: ovsds
Author-email: github@ovsds.ru
Requires-Python: >=3.9,<3.13
Classifier: License :: OSI Approved :: MIT License
Classifier: Programming Language :: Python :: 3
Classifier: Programming Language :: Python :: 3.9
Classifier: Programming Language :: Python :: 3.10
Classifier: Programming Language :: Python :: 3.11
Classifier: Programming Language :: Python :: 3.12
Requires-Dist: click (>=8.1.3,<9.0.0)
Requires-Dist: lazy-object-proxy (>=1.9.0,<2.0.0)
Requires-Dist: pydantic (>=2.0.3,<3.0.0)
Requires-Dist: python-dotenv (>=1.0.0,<2.0.0)
Requires-Dist: pyyaml (>=6.0,<7.0)
Project-URL: Repository, https://github.com/ovsds/secret-transfer
